pyagenity/__init__.py
pyagenity/adapters/__init__.py
pyagenity/adapters/llm/__init__.py
pyagenity/adapters/llm/base_converter.py
pyagenity/adapters/llm/litellm_converter.py
pyagenity/adapters/llm/model_response_converter.py
pyagenity/adapters/tools/__init__.py
pyagenity/adapters/tools/composio_adapter.py
pyagenity/adapters/tools/langchain_adapter.py
pyagenity/checkpointer/__init__.py
pyagenity/checkpointer/base_checkpointer.py
pyagenity/checkpointer/in_memory_checkpointer.py
pyagenity/checkpointer/pg_checkpointer.py
pyagenity/exceptions/__init__.py
pyagenity/exceptions/graph_error.py
pyagenity/exceptions/node_error.py
pyagenity/exceptions/recursion_error.py
pyagenity/exceptions/storage_exceptions.py
pyagenity/graph/__init__.py
pyagenity/graph/compiled_graph.py
pyagenity/graph/edge.py
pyagenity/graph/node.py
pyagenity/graph/state_graph.py
pyagenity/graph/tool_node/__init__.py
pyagenity/graph/tool_node/base.py
pyagenity/graph/tool_node/constants.py
pyagenity/graph/tool_node/deps.py
pyagenity/graph/tool_node/executors.py
pyagenity/graph/tool_node/schema.py
pyagenity/graph/utils/__init__.py
pyagenity/graph/utils/handler_mixins.py
pyagenity/graph/utils/invoke_handler.py
pyagenity/graph/utils/invoke_node_handler.py
pyagenity/graph/utils/stream_handler.py
pyagenity/graph/utils/stream_node_handler.py
pyagenity/graph/utils/stream_utils.py
pyagenity/graph/utils/utils.py
pyagenity/prebuilt/__init__.py
pyagenity/prebuilt/agent/__init__.py
pyagenity/prebuilt/agent/branch_join.py
pyagenity/prebuilt/agent/deep_research.py
pyagenity/prebuilt/agent/guarded.py
pyagenity/prebuilt/agent/map_reduce.py
pyagenity/prebuilt/agent/network.py
pyagenity/prebuilt/agent/plan_act_reflect.py
pyagenity/prebuilt/agent/rag.py
pyagenity/prebuilt/agent/react.py
pyagenity/prebuilt/agent/router.py
pyagenity/prebuilt/agent/sequential.py
pyagenity/prebuilt/agent/supervisor_team.py
pyagenity/prebuilt/agent/swarm.py
pyagenity/publisher/__init__.py
pyagenity/publisher/base_publisher.py
pyagenity-0.3.9.dist-info/licenses/LICENSE
pyagenity-0.3.9.dist-info/METADATA
pyagenity-0.3.9.dist-info/WHEEL
pyagenity-0.3.9.dist-info/top_level.txt
pyagenity-0.3.9.dist-info/RECORD
